README.md
setup.cfg
setup.py
kv_settings/__init__.py
kv_settings/admin.py
kv_settings/apps.py
kv_settings/models.py
kv_settings.egg-info/PKG-INFO
kv_settings.egg-info/SOURCES.txt
kv_settings.egg-info/dependency_links.txt
kv_settings.egg-info/requires.txt
kv_settings.egg-info/top_level.txt
kv_settings/management/__init__.py
kv_settings/management/commands/__init__.py
kv_settings/management/commands/create_mongo_indexes.py
kv_settings/migrations/0001_initial.py
kv_settings/migrations/__init__.py