Metadata-Version: 1.1
Name: kv-settings
Version: 2.0.0
Summary: Django Key Value Settings
Home-page: https://github.com/eshandas/django_key_value_settings
Author: Eshan Das
Author-email: eshandasnit@gmail.com
License: UNKNOWN
Download-URL: https://github.com/eshandas/django_key_value_settings/archive/2.0.0.tar.gz
Keywords: django,key value,settings
Platform: UNKNOWN
